{"namedChunkGroups":{"polyfill":{"name":"polyfill","assets":[{"name":"webpack-runtime-f761ed761e131621229e.js","size":4928},{"name":"polyfill-72b219bae196683411be.js","size":82649}],"filteredAssets":0,"assetsSize":87577,"filteredAuxiliaryAssets":2,"auxiliaryAssetsSize":221187},"app":{"name":"app","assets":[{"name":"webpack-runtime-f761ed761e131621229e.js","size":4928},{"name":"framework-89ddeb149991009fa125.js","size":128977},{"name":"app-b2c9958359abc9f5d8e2.js","size":68189}],"filteredAssets":0,"assetsSize":202094,"filteredAuxiliaryAssets":3,"auxiliaryAssetsSize":651324},"component---src-pages-404-js":{"name":"component---src-pages-404-js","assets":[{"name":"styles.73992bc09de8d6dce562.css","size":87867},{"name":"commons-41ccb7de0711edb26779.js","size":17527},{"name":"component---src-pages-404-js-614c237d7296d0d174a8.js","size":485}],"filteredAssets":0,"assetsSize":105879,"filteredAuxiliaryAssets":9,"auxiliaryAssetsSize":299671},"component---src-pages-index-js":{"name":"component---src-pages-index-js","assets":[{"name":"styles.73992bc09de8d6dce562.css","size":87867},{"name":"commons-41ccb7de0711edb26779.js","size":17527},{"name":"component---src-pages-index-js-fcf6f7ad75fa63b3bb82.js","size":3297}],"filteredAssets":0,"assetsSize":108691,"filteredAuxiliaryAssets":9,"auxiliaryAssetsSize":304422}},"assetsByChunkName":{"polyfill":["webpack-runtime-f761ed761e131621229e.js","polyfill-72b219bae196683411be.js"],"app":["webpack-runtime-f761ed761e131621229e.js","framework-89ddeb149991009fa125.js","app-b2c9958359abc9f5d8e2.js"],"component---src-pages-404-js":["styles.73992bc09de8d6dce562.css","commons-41ccb7de0711edb26779.js","component---src-pages-404-js-614c237d7296d0d174a8.js"],"component---src-pages-index-js":["styles.73992bc09de8d6dce562.css","commons-41ccb7de0711edb26779.js","component---src-pages-index-js-fcf6f7ad75fa63b3bb82.js"]},"childAssetsByChunkName":{}}